fluke5440b_async/__init__.py
fluke5440b_async/_version.py
fluke5440b_async/enums.py
fluke5440b_async/errors.py
fluke5440b_async/flags.py
fluke5440b_async/fluke_5440b.py
fluke5440b_async-1.0.3.dist-info/LICENSE
fluke5440b_async-1.0.3.dist-info/METADATA
fluke5440b_async-1.0.3.dist-info/WHEEL
fluke5440b_async-1.0.3.dist-info/top_level.txt
fluke5440b_async-1.0.3.dist-info/RECORD
