Metadata-Version: 2.1
Name: fluke5440b-async
Version: 1.0.3
Summary: A Python asyncio library for the Fluke 5440B voltage calibrator.
Author-email: Patrick Baus <patrick.baus@physik.tu-darmstadt.de>
License: GNU General Public License v3 (GPLv3)
Project-URL: Homepage, https://github.com/PatrickBaus/pyAsyncFluke5440B
Project-URL: Bug Tracker, https://github.com/PatrickBaus/pyAsyncFluke5440B/issues
Project-URL: Download, https://github.com/PatrickBaus/pyAsyncFluke5440B/releases
Keywords: Fluke 5440B,GPIB,API
Classifier: Programming Language :: Python :: 3
Classifier: Programming Language :: Python :: 3.8
Classifier: Programming Language :: Python :: 3.9
Classifier: Programming Language :: Python :: 3.10
Classifier: Programming Language :: Python :: 3.11
Classifier: Programming Language :: Python :: 3.12
Classifier: Development Status :: 5 - Production/Stable
Classifier: License :: OSI Approved :: GNU General Public License v3 (GPLv3)
Classifier: Operating System :: OS Independent
Classifier: Intended Audience :: Developers
Classifier: Intended Audience :: Science/Research
Classifier: Natural Language :: English
Classifier: Topic :: Home Automation
Classifier: Topic :: Scientific/Engineering
Requires-Python: >=3.7
License-File: LICENSE
Requires-Dist: typing-extensions ; python_version < "3.11"
Provides-Extra: dev
Requires-Dist: async-gpib ; extra == 'dev'
Requires-Dist: black ; extra == 'dev'
Requires-Dist: build ; extra == 'dev'
Requires-Dist: gpib-ctypes ; extra == 'dev'
Requires-Dist: isort ; extra == 'dev'
Requires-Dist: mypy ; extra == 'dev'
Requires-Dist: pre-commit ; extra == 'dev'
Requires-Dist: prologix-gpib-async ; extra == 'dev'
Requires-Dist: pylint ; extra == 'dev'
Requires-Dist: twine ; extra == 'dev'
Provides-Extra: doc
Requires-Dist: myst-parser ; extra == 'doc'
Requires-Dist: sphinx ; extra == 'doc'
Provides-Extra: linux-gpib
Requires-Dist: async-gpib ; extra == 'linux-gpib'
Requires-Dist: gpib-ctypes ; extra == 'linux-gpib'
Provides-Extra: prologix-gpib
Requires-Dist: prologix-gpib-async ; extra == 'prologix-gpib'
Provides-Extra: test
Requires-Dist: mypy ; extra == 'test'
Requires-Dist: pylint ; extra == 'test'
Requires-Dist: gpib-ctypes ; extra == 'test'
Requires-Dist: prologix-gpib-async ; extra == 'test'
Requires-Dist: setuptools ; extra == 'test'
